dominant_color/__init__.py
dominant_color/image_palette.py
dominant_color/kmeans_palette.py
dominant_color/mediancut_palette.py
dominant_color-0.0.8.dist-info/entry_points.txt
dominant_color-0.0.8.dist-info/WHEEL
dominant_color-0.0.8.dist-info/METADATA
dominant_color-0.0.8.dist-info/RECORD
