Metadata-Version: 2.1
Name: dominant_color
Version: 0.0.8
Summary: Just a demo of different dominant color extraction algorithms
Home-page: UNKNOWN
License: UNKNOWN
Author: Julien Palard
Author-email: julien@python.org
Requires-Python: >=3.6
Classifier: Programming Language :: Python :: 3.7
Classifier: Intended Audience :: Developers
Requires-Dist: scipy
Requires-Dist: matplotlib
Requires-Dist: pillow
